{"type": "Feature", "id": 12523690, "properties": {"woe:id": 12523690, "woe:parent_id": 379835, "woe:name": "Regina Airport", "woe:placetype": 14, "woe:placetype_name": "Airport", "woe:lang": "ENG", "iso:country": "GF", "meta:provider": ["geoplanet:7.3.1", "geoplanet:7.3.2", "geoplanet:7.4.0", "geoplanet:7.4.1", "geoplanet:7.5.1", "geoplanet:7.5.2", "geoplanet:7.6.0", "geoplanet:7.8.1", "geoplanet:7.9.0", "geoplanet:7.10.0", "geoplanet:8.0.0", "woeplanet:8.0.0"], "meta:indexed": "2020-08-20T20:28:14.159524", "woe:alias_ENG_V": ["REI Airport", "REI"], "meta:updated": "2020-08-22T01:49:57.905981", "woe:hierarchy": {"continent": 24865673, "country": 23424811, "town": 0, "planet": 1, "county": 55998448, "suburb": 0, "state": 2345321, "region": 0, "localadmin": 0}, "woe:timezone_id": 28350744, "woe:hash": "dbfbt9vdqj97", "woe:centroid": [-52.133301, 4.31667], "geom:latitude": 4.31667, "geom:longitude": -52.133301, "geom:hash": "dbfbt9vdqj97", "woe:latitude": 4.31667, "geom:centroid": [-52.133301, 4.31667], "woe:longitude": -52.133301, "woe:repo": "woeplanet-airport-gf"}, "geometry": {"coordinates": [-52.133301, 4.31667], "type": "Point"}}